mcgo/__init__.py
mcgo/gost/__init__.py
mcgo-0.1.2.dist-info/LICENSE
mcgo-0.1.2.dist-info/METADATA
mcgo-0.1.2.dist-info/WHEEL
mcgo-0.1.2.dist-info/top_level.txt
mcgo-0.1.2.dist-info/RECORD
