Metadata-Version: 2.1
Name: mcgo
Version: 0.1.2
Summary: encryption project
Home-page: https://py.m5k.ru/projects/mcgo
Author: 6d6b
Author-email: 6d6b31@gmail.com
License: UNKNOWN
Project-URL: Bug Tracker, https://py.m5k.ru/issues
Platform: UNKNOWN
Classifier: Programming Language :: Python :: 3
Classifier: License :: OSI Approved :: MIT License
Classifier: Operating System :: OS Independent
Requires-Python: >=3.6
